trio_jsonrpc/__init__.py
trio_jsonrpc/dispatch.py
trio_jsonrpc/main.py
trio_jsonrpc/sphinx_ext.py
trio_jsonrpc/transport/__init__.py
trio_jsonrpc/transport/memory.py
trio_jsonrpc/transport/ws.py
trio_jsonrpc-0.4.0.dist-info/LICENSE.md
trio_jsonrpc-0.4.0.dist-info/WHEEL
trio_jsonrpc-0.4.0.dist-info/METADATA
trio_jsonrpc-0.4.0.dist-info/RECORD
