Metadata-Version: 2.1
Name: trio-jsonrpc
Version: 0.4.0
Summary: JSON-RPC v2.0 for Trio
Home-page: https://github.com/hyperiongray/trio-jsonrpc
License: MIT
Author: Mark E. Haase
Author-email: mehaase@gmail.com
Requires-Python: >=3.7,<4.0
Classifier: Development Status :: 3 - Alpha
Classifier: Intended Audience :: Developers
Classifier: License :: OSI Approved :: MIT License
Classifier: Programming Language :: Python :: 3
Classifier: Programming Language :: Python :: 3.7
Classifier: Programming Language :: Python :: 3.8
Classifier: Topic :: Internet
Requires-Dist: sansio-jsonrpc (>=0.2.0,<0.3.0)
Requires-Dist: trio-websocket (>=0.8.0,<0.9.0)
